{"kind":"Article","sha256":"7b9cd77991519f20ad3a0d4345b9d563a2f23752dc98e0f4f42480a56781c9ed","slug":"api-unggun","location":"/content/siaga/day_1/api_unggun.md","dependencies":[],"frontmatter":{"title":"Api Unggun","authors":[{"id":"Tim Siaga CSC 2025","name":"Tim Siaga CSC 2025"}],"content_includes_title":false,"thumbnail":"/formasi_unggun-29db10a767786459e08a886ac8ff0062.jpeg","exports":[{"format":"md","filename":"api_unggun.md","url":"/api_unggun-a4e8dc2b5995cb6c3ba81f33759518d6.md"}]},"mdast":{"type":"root","children":[{"type":"block","children":[{"type":"paragraph","position":{"start":{"line":5,"column":1},"end":{"line":5,"column":1}},"children":[{"type":"text","value":"Setelah berkegiatan dengan riang di siang harinya, semua berkumpul untuk mengikuti Upacara Api Unggun dalam rangka memperingati Hari Baden Powell Ke-168","position":{"start":{"line":5,"column":1},"end":{"line":5,"column":1}},"key":"NBafZlpjU6"}],"key":"RmLXaNpiuV"},{"type":"heading","depth":2,"position":{"start":{"line":7,"column":1},"end":{"line":7,"column":1}},"children":[{"type":"text","value":"Formasi Upacara Api Unggun","position":{"start":{"line":7,"column":1},"end":{"line":7,"column":1}},"key":"HN2hb2oBJG"}],"identifier":"formasi-upacara-api-unggun","label":"Formasi Upacara Api Unggun","html_id":"formasi-upacara-api-unggun","implicit":true,"key":"BMHCOSNmBV"},{"type":"container","kind":"figure","children":[{"type":"image","url":"/formasi_unggun-29db10a767786459e08a886ac8ff0062.jpeg","alt":"Formasi pada saat Upacara Api Unggun nanti. Selamat mengikuti","data":{"altTextIsAutoGenerated":true},"key":"Jixr5Ca0SB","urlSource":"../../../_static/images/formasi_unggun.jpeg"},{"type":"caption","children":[{"type":"paragraph","position":{"start":{"line":10,"column":1},"end":{"line":10,"column":1}},"children":[{"type":"captionNumber","kind":"figure","label":"formasi-unggun","identifier":"formasi-unggun","html_id":"formasi-unggun","enumerator":"1","children":[{"type":"text","value":"Figure ","key":"M3pCmjnZjj"},{"type":"text","value":"1","key":"vLk2RVwMTh"},{"type":"text","value":":","key":"qVpRcVmoxU"}],"template":"Figure %s:","key":"dApMh2DARG"},{"type":"text","value":"Formasi pada saat Upacara Api Unggun nanti. Selamat mengikuti","position":{"start":{"line":10,"column":1},"end":{"line":10,"column":1}},"key":"CQOxYAzzP4"}],"key":"GpyNlQlrV2"}],"key":"ksiXyebRlR"}],"label":"formasi-unggun","identifier":"formasi-unggun","enumerator":"1","html_id":"formasi-unggun","key":"RRLHUQbrtV"},{"type":"heading","depth":2,"position":{"start":{"line":13,"column":1},"end":{"line":13,"column":1}},"children":[{"type":"text","value":"Alur Upacara Api Unggun","position":{"start":{"line":13,"column":1},"end":{"line":13,"column":1}},"key":"U35MS47U35"}],"identifier":"alur-upacara-api-unggun","label":"Alur Upacara Api Unggun","html_id":"alur-upacara-api-unggun","implicit":true,"key":"hmSFkmakNP"},{"type":"container","kind":"table","children":[{"type":"table","position":{"start":{"line":18,"column":1},"end":{"line":28,"column":1}},"children":[{"type":"tableRow","position":{"start":{"line":18,"column":1},"end":{"line":18,"column":1}},"children":[{"type":"tableCell","header":true,"align":"left","position":{"start":{"line":18,"column":1},"end":{"line":18,"column":1}},"children":[{"type":"text","value":"No.","position":{"start":{"line":18,"column":1},"end":{"line":18,"column":1}},"key":"OYnvpyPNKY"}],"key":"YBZObyqsIU"},{"type":"tableCell","header":true,"align":"center","position":{"start":{"line":18,"column":1},"end":{"line":18,"column":1}},"children":[{"type":"text","value":"Waktu","position":{"start":{"line":18,"column":1},"end":{"line":18,"column":1}},"key":"LyPdnGjJ4B"}],"key":"gefNvUef0z"},{"type":"tableCell","header":true,"align":"left","position":{"start":{"line":18,"column":1},"end":{"line":18,"column":1}},"children":[{"type":"text","value":"Keterangan","position":{"start":{"line":18,"column":1},"end":{"line":18,"column":1}},"key":"OpHF0e1Tla"}],"key":"s31k9pKNTR"}],"key":"t5EkRp44uY"},{"type":"tableRow","position":{"start":{"line":20,"column":1},"end":{"line":20,"column":1}},"children":[{"type":"tableCell","align":"left","position":{"start":{"line":20,"column":1},"end":{"line":20,"column":1}},"children":[{"type":"text","value":"1.","position":{"start":{"line":20,"column":1},"end":{"line":20,"column":1}},"key":"zgCTCTMK6u"}],"key":"AEUHcz8m3a"},{"type":"tableCell","align":"center","position":{"start":{"line":20,"column":1},"end":{"line":20,"column":1}},"children":[{"type":"text","value":"19.00","position":{"start":{"line":20,"column":1},"end":{"line":20,"column":1}},"key":"H5UKiSl9DP"}],"key":"LlLUOAPOwJ"},{"type":"tableCell","align":"left","position":{"start":{"line":20,"column":1},"end":{"line":20,"column":1}},"children":[{"type":"text","value":"Upacara dimulai","position":{"start":{"line":20,"column":1},"end":{"line":20,"column":1}},"key":"UvpZN2XkvK"}],"key":"pYA1lM8Ctz"}],"key":"LWVtnh7vMh"},{"type":"tableRow","position":{"start":{"line":21,"column":1},"end":{"line":21,"column":1}},"children":[{"type":"tableCell","align":"left","position":{"start":{"line":21,"column":1},"end":{"line":21,"column":1}},"children":[{"type":"text","value":"2.","position":{"start":{"line":21,"column":1},"end":{"line":21,"column":1}},"key":"OUDuCqyjej"}],"key":"TP1tketnCR"},{"type":"tableCell","align":"center","position":{"start":{"line":21,"column":1},"end":{"line":21,"column":1}},"children":[{"type":"text","value":"----","position":{"start":{"line":21,"column":1},"end":{"line":21,"column":1}},"key":"ZyOmWhdQvW"}],"key":"CZlBQJj4Dm"},{"type":"tableCell","align":"left","position":{"start":{"line":21,"column":1},"end":{"line":21,"column":1}},"children":[{"type":"text","value":"Penyalaan Api Unggun","position":{"start":{"line":21,"column":1},"end":{"line":21,"column":1}},"key":"zKctuJZbc3"}],"key":"gtqF8Pgizk"}],"key":"FUUpKXUWOr"},{"type":"tableRow","position":{"start":{"line":22,"column":1},"end":{"line":22,"column":1}},"children":[{"type":"tableCell","align":"left","position":{"start":{"line":22,"column":1},"end":{"line":22,"column":1}},"children":[{"type":"text","value":"3.","position":{"start":{"line":22,"column":1},"end":{"line":22,"column":1}},"key":"fsU5uyAow8"}],"key":"sN9nojvI0R"},{"type":"tableCell","align":"center","position":{"start":{"line":22,"column":1},"end":{"line":22,"column":1}},"children":[{"type":"text","value":"----","position":{"start":{"line":22,"column":1},"end":{"line":22,"column":1}},"key":"AilSyCPWaT"}],"key":"Qx35oAZ0sw"},{"type":"tableCell","align":"left","position":{"start":{"line":22,"column":1},"end":{"line":22,"column":1}},"children":[{"type":"text","value":"Sambutan Ketua Panitia","position":{"start":{"line":22,"column":1},"end":{"line":22,"column":1}},"key":"y6KrZe5Bdf"}],"key":"ElBPP64kYx"}],"key":"cT7Gu03h53"},{"type":"tableRow","position":{"start":{"line":23,"column":1},"end":{"line":23,"column":1}},"children":[{"type":"tableCell","align":"left","position":{"start":{"line":23,"column":1},"end":{"line":23,"column":1}},"children":[{"type":"text","value":"4.","position":{"start":{"line":23,"column":1},"end":{"line":23,"column":1}},"key":"RQPAK3d8eP"}],"key":"A3QFTQk84q"},{"type":"tableCell","align":"center","position":{"start":{"line":23,"column":1},"end":{"line":23,"column":1}},"children":[{"type":"text","value":"----","position":{"start":{"line":23,"column":1},"end":{"line":23,"column":1}},"key":"MVJx3EUjbr"}],"key":"G4cMJXalzL"},{"type":"tableCell","align":"left","position":{"start":{"line":23,"column":1},"end":{"line":23,"column":1}},"children":[{"type":"text","value":"Narasi Lord Baden Powell","position":{"start":{"line":23,"column":1},"end":{"line":23,"column":1}},"key":"j6JLaft8bd"}],"key":"IXezdMQFoT"}],"key":"VSJbHAvI4o"},{"type":"tableRow","position":{"start":{"line":24,"column":1},"end":{"line":24,"column":1}},"children":[{"type":"tableCell","align":"left","position":{"start":{"line":24,"column":1},"end":{"line":24,"column":1}},"children":[{"type":"text","value":"5.","position":{"start":{"line":24,"column":1},"end":{"line":24,"column":1}},"key":"L7GhNV5Xh6"}],"key":"p3XybTAg4g"},{"type":"tableCell","align":"center","position":{"start":{"line":24,"column":1},"end":{"line":24,"column":1}},"children":[{"type":"text","value":"----","position":{"start":{"line":24,"column":1},"end":{"line":24,"column":1}},"key":"XaJLOYL36P"}],"key":"bREk08eLkZ"},{"type":"tableCell","align":"left","position":{"start":{"line":24,"column":1},"end":{"line":24,"column":1}},"children":[{"type":"text","value":"Amanat oleh Pembina Upacara","position":{"start":{"line":24,"column":1},"end":{"line":24,"column":1}},"key":"m9cMNr9ruV"}],"key":"Cy6kLsPKuX"}],"key":"GH63dJ8qZl"},{"type":"tableRow","position":{"start":{"line":25,"column":1},"end":{"line":25,"column":1}},"children":[{"type":"tableCell","align":"left","position":{"start":{"line":25,"column":1},"end":{"line":25,"column":1}},"children":[{"type":"text","value":"6.","position":{"start":{"line":25,"column":1},"end":{"line":25,"column":1}},"key":"swjbwMyNuS"}],"key":"U7xsNyUDey"},{"type":"tableCell","align":"center","position":{"start":{"line":25,"column":1},"end":{"line":25,"column":1}},"children":[{"type":"text","value":"----","position":{"start":{"line":25,"column":1},"end":{"line":25,"column":1}},"key":"xYSV99amvJ"}],"key":"HJNHWyV9xh"},{"type":"tableCell","align":"left","position":{"start":{"line":25,"column":1},"end":{"line":25,"column":1}},"children":[{"type":"text","value":"Himne Pramuka","position":{"start":{"line":25,"column":1},"end":{"line":25,"column":1}},"key":"tcvoaHLD2l"}],"key":"GT8L0C38XJ"}],"key":"FTxcL1GHTE"},{"type":"tableRow","position":{"start":{"line":26,"column":1},"end":{"line":26,"column":1}},"children":[{"type":"tableCell","align":"left","position":{"start":{"line":26,"column":1},"end":{"line":26,"column":1}},"children":[{"type":"text","value":"7.","position":{"start":{"line":26,"column":1},"end":{"line":26,"column":1}},"key":"LGuKxSNoHF"}],"key":"kRUAbGvEVV"},{"type":"tableCell","align":"center","position":{"start":{"line":26,"column":1},"end":{"line":26,"column":1}},"children":[{"type":"text","value":"----","position":{"start":{"line":26,"column":1},"end":{"line":26,"column":1}},"key":"lvdAG8KBhE"}],"key":"ZUpAa0r6sW"},{"type":"tableCell","align":"left","position":{"start":{"line":26,"column":1},"end":{"line":26,"column":1}},"children":[{"type":"text","value":"Do’a","position":{"start":{"line":26,"column":1},"end":{"line":26,"column":1}},"key":"f2YZr8DwDd"}],"key":"b5s0viUBQi"}],"key":"nEVxXGEGku"},{"type":"tableRow","position":{"start":{"line":27,"column":1},"end":{"line":27,"column":1}},"children":[{"type":"tableCell","align":"left","position":{"start":{"line":27,"column":1},"end":{"line":27,"column":1}},"children":[{"type":"text","value":"8.","position":{"start":{"line":27,"column":1},"end":{"line":27,"column":1}},"key":"usbAWsxDWr"}],"key":"Wje1lb6We0"},{"type":"tableCell","align":"center","position":{"start":{"line":27,"column":1},"end":{"line":27,"column":1}},"children":[{"type":"text","value":"----","position":{"start":{"line":27,"column":1},"end":{"line":27,"column":1}},"key":"qhIGcX6KGY"}],"key":"bY6XPGuoUA"},{"type":"tableCell","align":"left","position":{"start":{"line":27,"column":1},"end":{"line":27,"column":1}},"children":[{"type":"text","value":"Penutup","position":{"start":{"line":27,"column":1},"end":{"line":27,"column":1}},"key":"shycPr9tJ5"}],"key":"Mhm3zfHEpj"}],"key":"DBYf5cva0Y"},{"type":"tableRow","position":{"start":{"line":28,"column":1},"end":{"line":28,"column":1}},"children":[{"type":"tableCell","align":"left","position":{"start":{"line":28,"column":1},"end":{"line":28,"column":1}},"children":[{"type":"text","value":"9.","position":{"start":{"line":28,"column":1},"end":{"line":28,"column":1}},"key":"XvgYyRuEsE"}],"key":"yw2hnSiOYd"},{"type":"tableCell","align":"center","position":{"start":{"line":28,"column":1},"end":{"line":28,"column":1}},"children":[{"type":"text","value":"----","position":{"start":{"line":28,"column":1},"end":{"line":28,"column":1}},"key":"rswKfIxqUt"}],"key":"jy9GrOVIsy"},{"type":"tableCell","align":"left","position":{"start":{"line":28,"column":1},"end":{"line":28,"column":1}},"children":[{"type":"text","value":"Lanjut ke Pentas Kolaborasi","position":{"start":{"line":28,"column":1},"end":{"line":28,"column":1}},"key":"Lt2OoIl9lj"}],"key":"D1NFdp9AWI"}],"key":"FU92k6J5fF"}],"key":"WPaePx4LJ4"}],"label":"alur_upacara_api_unggun","identifier":"alur_upacara_api_unggun","enumerator":"1","html_id":"alur-upacara-api-unggun","key":"afqeIKyO94"},{"type":"list","ordered":false,"spread":false,"position":{"start":{"line":32,"column":1},"end":{"line":37,"column":1}},"children":[{"type":"listItem","spread":true,"position":{"start":{"line":32,"column":1},"end":{"line":32,"column":1}},"children":[{"type":"text","value":"Narator: Ayu dan Odilia","position":{"start":{"line":32,"column":1},"end":{"line":32,"column":1}},"key":"V3RT2rEWkx"}],"key":"nG367yS5rZ"},{"type":"listItem","spread":true,"position":{"start":{"line":33,"column":1},"end":{"line":33,"column":1}},"children":[{"type":"text","value":"Pemain biola: Joel","position":{"start":{"line":33,"column":1},"end":{"line":33,"column":1}},"key":"mlxNgmR94D"}],"key":"atcJp4SP5K"},{"type":"listItem","spread":true,"position":{"start":{"line":34,"column":1},"end":{"line":34,"column":1}},"children":[{"type":"text","value":"Pembawa lilin dan pembaca Dasa Darma: Dewan Penggalang","position":{"start":{"line":34,"column":1},"end":{"line":34,"column":1}},"key":"wZY0fl3yKX"}],"key":"a7pcwF67XL"},{"type":"listItem","spread":true,"position":{"start":{"line":35,"column":1},"end":{"line":35,"column":1}},"children":[{"type":"text","value":"Pemimpin lagu: Bina","position":{"start":{"line":35,"column":1},"end":{"line":35,"column":1}},"key":"NFBKdNO9tx"}],"key":"YabHlHZ1tD"},{"type":"listItem","spread":true,"position":{"start":{"line":36,"column":1},"end":{"line":36,"column":1}},"children":[{"type":"text","value":"Himne Pramuka: Musikus iringan dari Kak Ika","position":{"start":{"line":36,"column":1},"end":{"line":36,"column":1}},"key":"nM6Po8vWqp"}],"key":"igWs9sVmBk"},{"type":"listItem","spread":true,"position":{"start":{"line":37,"column":1},"end":{"line":37,"column":1}},"children":[{"type":"text","value":"Musik: Kak Eko","position":{"start":{"line":37,"column":1},"end":{"line":37,"column":1}},"key":"X21szNHt4u"}],"key":"dWxAAeaaO0"}],"key":"xJ2xpTg4HM"}],"key":"c9XK1khmzp"}],"key":"y0JF1pXfLv"},"references":{"cite":{"order":[],"data":{}}}}