{"kind":"Article","sha256":"54520efec6b6ff94a6a4ed36f9090eadf0ba76ce211368c2ccad6ed86b13a1fe","slug":"inventory","location":"/content/inventory.md","dependencies":[],"frontmatter":{"title":"Perlengkapan","content_includes_title":false,"exports":[{"format":"md","filename":"inventory.md","url":"/inventory-1db5bc47ea8b15a264062b5afc5c7bbf.md"}]},"mdast":{"type":"root","children":[{"type":"block","children":[{"type":"paragraph","position":{"start":{"line":2,"column":1},"end":{"line":3,"column":1}},"children":[{"type":"text","value":"Segala sesuatu yang akan diperlukan saat kemah nanti ada di sini\nStay Tuned!","position":{"start":{"line":2,"column":1},"end":{"line":2,"column":1}},"key":"pZahwl5bMK"}],"key":"kszrqUj7dB"}],"key":"GgrsGz1dGE"}],"key":"yygClWCBwL"},"references":{"cite":{"order":[],"data":{}}}}