{"kind":"Article","sha256":"99027474c4bae1ebc788a0ff54292b2e377ab4803bd9acd413f462d7af619189","slug":"obstacle-game","location":"/content/day_1/obstacle_game.md","dependencies":[],"frontmatter":{"title":"Obstacle Game Tracker","content_includes_title":false,"exports":[{"format":"md","filename":"obstacle_game.md","url":"/obstacle_game-dd66241463b06f739393d7fecaa1b63f.md"}]},"mdast":{"type":"root","children":[{"type":"block","children":[{"type":"iframe","src":"https://docs.google.com/spreadsheets/d/e/2PACX-1vS3Ysm4EdtkiyTfdoCcb9TIpqTeSrX-KKLsomWHoxnZ2w5-_xIjsvVe6GIQOzQ0reh_TTquElzfLZmJ/pubhtml?gid=98147011&single=true&single=true&range=D4:J38","width":"100%","key":"vjjTuCNzi7"}],"key":"KLGrPjicQA"}],"key":"gmBhkqSsyQ"},"references":{"cite":{"order":[],"data":{}}}}